LICENSE.txt
MANIFEST.in
README.rst
setup.py
sqlquerybuilder/__init__.py
sqlquerybuilder/tests.py
sqlquerybuilder.egg-info/PKG-INFO
sqlquerybuilder.egg-info/SOURCES.txt
sqlquerybuilder.egg-info/dependency_links.txt
sqlquerybuilder.egg-info/top_level.txt