Metadata-Version: 1.1
Name: sqlquerybuilder
Version: 0.0.13
Summary: SQL Query Builder inspired on django ORM Syntax
Home-page: https://github.com/josesanch/sqlquerybuilder
Author: José Sánchez Moreno
Author-email: jose@o2w.es
License: MIT
Platform: All platforms
Classifier: Development Status :: 4 - Beta
Classifier: Intended Audience :: Developers
Classifier: License :: OSI Approved :: Python Software Foundation License
Classifier: Operating System :: MacOS :: MacOS X
Classifier: Operating System :: Microsoft :: Windows
Classifier: Operating System :: POSIX
Classifier: Programming Language :: Python
Classifier: Programming Language :: SQL
